{"intervals": [{"streams": [{"seconds": 5.00008, "end": 5.00009, "start": 0, "snd_cwnd": 617481, "retransmits": 0, "socket": 4, "bits_per_second": 515929000.0, "bytes": 322461400, "omitted": false}, {"seconds": 5.00009, "end": 5.00009, "start": 0, "snd_cwnd": 536940, "retransmits": 0, "socket": 6, "bits_per_second": 511009000.0, "bytes": 319386107, "omitted": false}, {"seconds": 5.00009, "end": 5.00009, "start": 0, "snd_cwnd": 653277, "retransmits": 0, "socket": 8, "bits_per_second": 709768000.0, "bytes": 443612962, "omitted": false}, {"seconds": 5.00009, "end": 5.00009, "start": 0, "snd_cwnd": 1476585, "retransmits": 0, "socket": 10, "bits_per_second": 1337870000.0, "bytes": 836186668, "omitted": false}, {"seconds": 5.00009, "end": 5.00009, "start": 0, "snd_cwnd": 1136523, "retransmits": 0, "socket": 12, "bits_per_second": 1004630000.0, "bytes": 627903308, "omitted": false}, {"seconds": 5.00009, "end": 5.00009, "start": 0, "snd_cwnd": 456399, "retransmits": 0, "socket": 14, "bits_per_second": 441437000.0, "bytes": 275902916, "omitted": false}, {"seconds": 5.00009, "end": 5.00009, "start": 0, "snd_cwnd": 796461, "retransmits": 0, "socket": 16, "bits_per_second": 1082700000.0, "bytes": 676698616, "omitted": false}, {"seconds": 5.00009, "end": 5.00009, "start": 0, "snd_cwnd": 617481, "retransmits": 0, "socket": 18, "bits_per_second": 706317000.0, "bytes": 441456253, "omitted": false}, {"seconds": 5.0001, "end": 5.0001, "start": 0, "snd_cwnd": 706971, "retransmits": 0, "socket": 20, "bits_per_second": 591170000.0, "bytes": 369488395, "omitted": false}, {"seconds": 5.0001, "end": 5.0001, "start": 0, "snd_cwnd": 689073, "retransmits": 0, "socket": 22, "bits_per_second": 589815000.0, "bytes": 368641403, "omitted": false}], "sum": {"seconds": 5.00008, "end": 5.00009, "start": 0, "retransmits": 0, "bits_per_second": 7490650000.0, "omitted": false, "bytes": 4681738028}}], "end": {"streams": [{"sender": {"seconds": 5.00009, "end": 5.00009, "start": 0, "retransmits": 0, "socket": 4, "bits_per_second": 515929000.0, "bytes": 322461400}, "receiver": {"seconds": 5.00009, "end": 5.00009, "start": 0, "socket": 4, "bits_per_second": 512765000.0, "bytes": 320483671}}, {"sender": {"seconds": 5.00009, "end": 5.00009, "start": 0, "retransmits": 0, "socket": 6, "bits_per_second": 511009000.0, "bytes": 319386107}, "receiver": {"seconds": 5.00009, "end": 5.00009, "start": 0, "socket": 6, "bits_per_second": 508818000.0, "bytes": 318016910}}, {"sender": {"seconds": 5.00009, "end": 5.00009, "start": 0, "retransmits": 0, "socket": 8, "bits_per_second": 709769000.0, "bytes": 443612962}, "receiver": {"seconds": 5.00009, "end": 5.00009, "start": 0, "socket": 8, "bits_per_second": 707449000.0, "bytes": 442163224}}, {"sender": {"seconds": 5.00009, "end": 5.00009, "start": 0, "retransmits": 0, "socket": 10, "bits_per_second": 1337880000.0, "bytes": 836186668}, "receiver": {"seconds": 5.00009, "end": 5.00009, "start": 0, "socket": 10, "bits_per_second": 1331950000.0, "bytes": 832482808}}, {"sender": {"seconds": 5.00009, "end": 5.00009, "start": 0, "retransmits": 0, "socket": 12, "bits_per_second": 1004630000.0, "bytes": 627903308}, "receiver": {"seconds": 5.00009, "end": 5.00009, "start": 0, "socket": 12, "bits_per_second": 998580000.0, "bytes": 624123241}}, {"sender": {"seconds": 5.00009, "end": 5.00009, "start": 0, "retransmits": 0, "socket": 14, "bits_per_second": 441437000.0, "bytes": 275902916}, "receiver": {"seconds": 5.00009, "end": 5.00009, "start": 0, "socket": 14, "bits_per_second": 439118000.0, "bytes": 274453178}}, {"sender": {"seconds": 5.00009, "end": 5.00009, "start": 0, "retransmits": 0, "socket": 16, "bits_per_second": 1082700000.0, "bytes": 676698616}, "receiver": {"seconds": 5.00009, "end": 5.00009, "start": 0, "socket": 16, "bits_per_second": 1079580000.0, "bytes": 674747734}}, {"sender": {"seconds": 5.00009, "end": 5.00009, "start": 0, "retransmits": 0, "socket": 18, "bits_per_second": 706318000.0, "bytes": 441456253}, "receiver": {"seconds": 5.00009, "end": 5.00009, "start": 0, "socket": 18, "bits_per_second": 703827000.0, "bytes": 439899127}}, {"sender": {"seconds": 5.00009, "end": 5.00009, "start": 0, "retransmits": 0, "socket": 20, "bits_per_second": 591171000.0, "bytes": 369488395}, "receiver": {"seconds": 5.00009, "end": 5.00009, "start": 0, "socket": 20, "bits_per_second": 587477000.0, "bytes": 367179553}}, {"sender": {"seconds": 5.00009, "end": 5.00009, "start": 0, "retransmits": 0, "socket": 22, "bits_per_second": 589816000.0, "bytes": 368641403}, "receiver": {"seconds": 5.00009, "end": 5.00009, "start": 0, "socket": 22, "bits_per_second": 586809000.0, "bytes": 366762113}}], "cpu_utilization_percent": {"host_system": 30.485, "host_user": 0.414526, "host_total": 30.8995, "remote_total": 11.8055, "remote_system": 10.9203, "remote_user": 0.885128}, "sum_sent": {"seconds": 5.00009, "end": 5.00009, "start": 0, "retransmits": 0, "bits_per_second": 7490650000.0, "bytes": 4681738028}, "sum_received": {"bytes": 4660311559, "seconds": 5.00009, "end": 5.00009, "start": 0, "bits_per_second": 7456370000.0}}, "start": {"tcp_mss_default": 8949, "connecting_to": {"port": 5201, "host": "172.31.67.222"}, "system_info": "Linux ip-172-31-70-219 3.13.0-156-generic #206-Ubuntu SMP Fri Aug 17 08:51:32 UTC 2018 x86_64 x86_64 x86_64 GNU/Linux\n", "test_start": {"duration": 5, "reverse": 0, "protocol": "TCP", "num_streams": 10, "blocks": 0, "bytes": 0, "omit": 0, "blksize": 131072}, "timestamp": {"time": "Sun, 07 Oct 2018 14:02:29 GMT", "timesecs": 1538920949}, "connected": [{"remote_host": "172.31.67.222", "local_port": 43902, "local_host": "172.31.70.219", "socket": 4, "remote_port": 5201}, {"remote_host": "172.31.67.222", "local_port": 43903, "local_host": "172.31.70.219", "socket": 6, "remote_port": 5201}, {"remote_host": "172.31.67.222", "local_port": 43904, "local_host": "172.31.70.219", "socket": 8, "remote_port": 5201}, {"remote_host": "172.31.67.222", "local_port": 43905, "local_host": "172.31.70.219", "socket": 10, "remote_port": 5201}, {"remote_host": "172.31.67.222", "local_port": 43906, "local_host": "172.31.70.219", "socket": 12, "remote_port": 5201}, {"remote_host": "172.31.67.222", "local_port": 43907, "local_host": "172.31.70.219", "socket": 14, "remote_port": 5201}, {"remote_host": "172.31.67.222", "local_port": 43908, "local_host": "172.31.70.219", "socket": 16, "remote_port": 5201}, {"remote_host": "172.31.67.222", "local_port": 43909, "local_host": "172.31.70.219", "socket": 18, "remote_port": 5201}, {"remote_host": "172.31.67.222", "local_port": 43910, "local_host": "172.31.70.219", "socket": 20, "remote_port": 5201}, {"remote_host": "172.31.67.222", "local_port": 43911, "local_host": "172.31.70.219", "socket": 22, "remote_port": 5201}], "version": "iperf 3.0.7", "cookie": "ip-172-31-70-219.1538920949.723134.6"}}