{"intervals": [{"streams": [{"seconds": 5.00009, "end": 5.00009, "start": 0, "snd_cwnd": 456399, "retransmits": 0, "socket": 4, "bits_per_second": 634669000.0, "bytes": 396675457, "omitted": false}, {"seconds": 5.00009, "end": 5.00009, "start": 0, "snd_cwnd": 599583, "retransmits": 0, "socket": 6, "bits_per_second": 638578000.0, "bytes": 399118534, "omitted": false}, {"seconds": 5.00009, "end": 5.00009, "start": 0, "snd_cwnd": 402705, "retransmits": 0, "socket": 8, "bits_per_second": 419911000.0, "bytes": 262449406, "omitted": false}, {"seconds": 5.0001, "end": 5.0001, "start": 0, "snd_cwnd": 429552, "retransmits": 0, "socket": 10, "bits_per_second": 422952000.0, "bytes": 264349757, "omitted": false}, {"seconds": 5.0001, "end": 5.0001, "start": 0, "snd_cwnd": 993339, "retransmits": 0, "socket": 12, "bits_per_second": 1242440000.0, "bytes": 776542609, "omitted": false}, {"seconds": 5.0001, "end": 5.0001, "start": 0, "snd_cwnd": 948594, "retransmits": 0, "socket": 14, "bits_per_second": 1100060000.0, "bytes": 687550590, "omitted": false}, {"seconds": 5.0001, "end": 5.0001, "start": 0, "snd_cwnd": 984390, "retransmits": 0, "socket": 16, "bits_per_second": 1355020000.0, "bytes": 846905433, "omitted": false}, {"seconds": 5.0001, "end": 5.0001, "start": 0, "snd_cwnd": 304266, "retransmits": 0, "socket": 18, "bits_per_second": 375057000.0, "bytes": 234415352, "omitted": false}, {"seconds": 5.0001, "end": 5.0001, "start": 0, "snd_cwnd": 608532, "retransmits": 0, "socket": 20, "bits_per_second": 493196000.0, "bytes": 308253551, "omitted": false}, {"seconds": 5.0001, "end": 5.0001, "start": 0, "snd_cwnd": 903849, "retransmits": 0, "socket": 22, "bits_per_second": 802610000.0, "bytes": 501641441, "omitted": false}], "sum": {"seconds": 5.00009, "end": 5.00009, "start": 0, "retransmits": 0, "bits_per_second": 7484510000.0, "omitted": false, "bytes": 4677902130}}], "end": {"streams": [{"sender": {"seconds": 5.00009, "end": 5.00009, "start": 0, "retransmits": 0, "socket": 4, "bits_per_second": 634669000.0, "bytes": 396675457}, "receiver": {"seconds": 5.00009, "end": 5.00009, "start": 0, "socket": 4, "bits_per_second": 632908000.0, "bytes": 395574730}}, {"sender": {"seconds": 5.00009, "end": 5.00009, "start": 0, "retransmits": 0, "socket": 6, "bits_per_second": 638578000.0, "bytes": 399118534}, "receiver": {"seconds": 5.00009, "end": 5.00009, "start": 0, "socket": 6, "bits_per_second": 636330000.0, "bytes": 397713541}}, {"sender": {"seconds": 5.00009, "end": 5.00009, "start": 0, "retransmits": 0, "socket": 8, "bits_per_second": 419912000.0, "bytes": 262449406}, "receiver": {"seconds": 5.00009, "end": 5.00009, "start": 0, "socket": 8, "bits_per_second": 418594000.0, "bytes": 261626098}}, {"sender": {"seconds": 5.00009, "end": 5.00009, "start": 0, "retransmits": 0, "socket": 10, "bits_per_second": 422952000.0, "bytes": 264349757}, "receiver": {"seconds": 5.00009, "end": 5.00009, "start": 0, "socket": 10, "bits_per_second": 421449000.0, "bytes": 263410112}}, {"sender": {"seconds": 5.00009, "end": 5.00009, "start": 0, "retransmits": 0, "socket": 12, "bits_per_second": 1242450000.0, "bytes": 776542609}, "receiver": {"seconds": 5.00009, "end": 5.00009, "start": 0, "socket": 12, "bits_per_second": 1239210000.0, "bytes": 774520135}}, {"sender": {"seconds": 5.00009, "end": 5.00009, "start": 0, "retransmits": 0, "socket": 14, "bits_per_second": 1100060000.0, "bytes": 687550590}, "receiver": {"seconds": 5.00009, "end": 5.00009, "start": 0, "socket": 14, "bits_per_second": 1096050000.0, "bytes": 685044870}}, {"sender": {"seconds": 5.00009, "end": 5.00009, "start": 0, "retransmits": 0, "socket": 16, "bits_per_second": 1355020000.0, "bytes": 846905433}, "receiver": {"seconds": 5.00009, "end": 5.00009, "start": 0, "socket": 16, "bits_per_second": 1351590000.0, "bytes": 844757673}}, {"sender": {"seconds": 5.00009, "end": 5.00009, "start": 0, "retransmits": 0, "socket": 18, "bits_per_second": 375058000.0, "bytes": 234415352}, "receiver": {"seconds": 5.00009, "end": 5.00009, "start": 0, "socket": 18, "bits_per_second": 373912000.0, "bytes": 233699432}}, {"sender": {"seconds": 5.00009, "end": 5.00009, "start": 0, "retransmits": 0, "socket": 20, "bits_per_second": 493197000.0, "bytes": 308253551}, "receiver": {"seconds": 5.00009, "end": 5.00009, "start": 0, "socket": 20, "bits_per_second": 490004000.0, "bytes": 306257924}}, {"sender": {"seconds": 5.00009, "end": 5.00009, "start": 0, "retransmits": 0, "socket": 22, "bits_per_second": 802612000.0, "bytes": 501641441}, "receiver": {"seconds": 5.00009, "end": 5.00009, "start": 0, "socket": 22, "bits_per_second": 798045000.0, "bytes": 498786710}}], "cpu_utilization_percent": {"host_system": 31.5929, "host_user": 0.553343, "host_total": 32.1462, "remote_total": 11.7487, "remote_system": 10.9551, "remote_user": 0.793571}, "sum_sent": {"seconds": 5.00009, "end": 5.00009, "start": 0, "retransmits": 0, "bits_per_second": 7484510000.0, "bytes": 4677902130}, "sum_received": {"bytes": 4661391225, "seconds": 5.00009, "end": 5.00009, "start": 0, "bits_per_second": 7458090000.0}}, "start": {"tcp_mss_default": 8949, "connecting_to": {"port": 5201, "host": "172.31.67.222"}, "system_info": "Linux ip-172-31-70-219 3.13.0-156-generic #206-Ubuntu SMP Fri Aug 17 08:51:32 UTC 2018 x86_64 x86_64 x86_64 GNU/Linux\n", "test_start": {"duration": 5, "reverse": 0, "protocol": "TCP", "num_streams": 10, "blocks": 0, "bytes": 0, "omit": 0, "blksize": 131072}, "timestamp": {"time": "Sun, 07 Oct 2018 01:53:59 GMT", "timesecs": 1538877239}, "connected": [{"remote_host": "172.31.67.222", "local_port": 54648, "local_host": "172.31.70.219", "socket": 4, "remote_port": 5201}, {"remote_host": "172.31.67.222", "local_port": 54649, "local_host": "172.31.70.219", "socket": 6, "remote_port": 5201}, {"remote_host": "172.31.67.222", "local_port": 54650, "local_host": "172.31.70.219", "socket": 8, "remote_port": 5201}, {"remote_host": "172.31.67.222", "local_port": 54651, "local_host": "172.31.70.219", "socket": 10, "remote_port": 5201}, {"remote_host": "172.31.67.222", "local_port": 54652, "local_host": "172.31.70.219", "socket": 12, "remote_port": 5201}, {"remote_host": "172.31.67.222", "local_port": 54653, "local_host": "172.31.70.219", "socket": 14, "remote_port": 5201}, {"remote_host": "172.31.67.222", "local_port": 54654, "local_host": "172.31.70.219", "socket": 16, "remote_port": 5201}, {"remote_host": "172.31.67.222", "local_port": 54655, "local_host": "172.31.70.219", "socket": 18, "remote_port": 5201}, {"remote_host": "172.31.67.222", "local_port": 54656, "local_host": "172.31.70.219", "socket": 20, "remote_port": 5201}, {"remote_host": "172.31.67.222", "local_port": 54657, "local_host": "172.31.70.219", "socket": 22, "remote_port": 5201}], "version": "iperf 3.0.7", "cookie": "ip-172-31-70-219.1538877239.770405.1"}}