{"intervals": [{"streams": [{"seconds": 5.00009, "end": 5.00009, "start": 0, "snd_cwnd": 411654, "retransmits": 0, "socket": 4, "bits_per_second": 383429000.0, "bytes": 239647354, "omitted": false}, {"seconds": 5.0001, "end": 5.0001, "start": 0, "snd_cwnd": 554838, "retransmits": 0, "socket": 6, "bits_per_second": 840248000.0, "bytes": 525165199, "omitted": false}, {"seconds": 5.0001, "end": 5.0001, "start": 0, "snd_cwnd": 492195, "retransmits": 0, "socket": 8, "bits_per_second": 510005000.0, "bytes": 318759677, "omitted": false}, {"seconds": 5.0001, "end": 5.0001, "start": 0, "snd_cwnd": 1127574, "retransmits": 0, "socket": 10, "bits_per_second": 847263000.0, "bytes": 529549780, "omitted": false}, {"seconds": 5.0001, "end": 5.0001, "start": 0, "snd_cwnd": 411654, "retransmits": 0, "socket": 12, "bits_per_second": 383405000.0, "bytes": 239632619, "omitted": false}, {"seconds": 5.0001, "end": 5.0001, "start": 0, "snd_cwnd": 742767, "retransmits": 0, "socket": 14, "bits_per_second": 672544000.0, "bytes": 420348725, "omitted": false}, {"seconds": 5.0001, "end": 5.0001, "start": 0, "snd_cwnd": 340062, "retransmits": 0, "socket": 16, "bits_per_second": 305318000.0, "bytes": 190827936, "omitted": false}, {"seconds": 5.0001, "end": 5.0001, "start": 0, "snd_cwnd": 402705, "retransmits": 0, "socket": 18, "bits_per_second": 439236000.0, "bytes": 274527933, "omitted": false}, {"seconds": 5.0001, "end": 5.0001, "start": 0, "snd_cwnd": 1977729, "retransmits": 0, "socket": 20, "bits_per_second": 2529180000.0, "bytes": 1580768821, "omitted": false}, {"seconds": 5.0001, "end": 5.0001, "start": 0, "snd_cwnd": 411654, "retransmits": 0, "socket": 22, "bits_per_second": 565516000.0, "bytes": 353454950, "omitted": false}], "sum": {"seconds": 5.00009, "end": 5.00009, "start": 0, "retransmits": 0, "bits_per_second": 7476150000.0, "omitted": false, "bytes": 4672682994}}], "end": {"streams": [{"sender": {"seconds": 5.00009, "end": 5.00009, "start": 0, "retransmits": 0, "socket": 4, "bits_per_second": 383429000.0, "bytes": 239647354}, "receiver": {"seconds": 5.00009, "end": 5.00009, "start": 0, "socket": 4, "bits_per_second": 381367000.0, "bytes": 238358698}}, {"sender": {"seconds": 5.00009, "end": 5.00009, "start": 0, "retransmits": 0, "socket": 6, "bits_per_second": 840249000.0, "bytes": 525165199}, "receiver": {"seconds": 5.00009, "end": 5.00009, "start": 0, "socket": 6, "bits_per_second": 837571000.0, "bytes": 523491736}}, {"sender": {"seconds": 5.00009, "end": 5.00009, "start": 0, "retransmits": 0, "socket": 8, "bits_per_second": 510006000.0, "bytes": 318759677}, "receiver": {"seconds": 5.00009, "end": 5.00009, "start": 0, "socket": 8, "bits_per_second": 508016000.0, "bytes": 317515766}}, {"sender": {"seconds": 5.00009, "end": 5.00009, "start": 0, "retransmits": 0, "socket": 10, "bits_per_second": 847264000.0, "bytes": 529549780}, "receiver": {"seconds": 5.00009, "end": 5.00009, "start": 0, "socket": 10, "bits_per_second": 841852000.0, "bytes": 526167487}}, {"sender": {"seconds": 5.00009, "end": 5.00009, "start": 0, "retransmits": 0, "socket": 12, "bits_per_second": 383405000.0, "bytes": 239632619}, "receiver": {"seconds": 5.00009, "end": 5.00009, "start": 0, "socket": 12, "bits_per_second": 381429000.0, "bytes": 238397657}}, {"sender": {"seconds": 5.00009, "end": 5.00009, "start": 0, "retransmits": 0, "socket": 14, "bits_per_second": 672545000.0, "bytes": 420348725}, "receiver": {"seconds": 5.00009, "end": 5.00009, "start": 0, "socket": 14, "bits_per_second": 668894000.0, "bytes": 418066730}}, {"sender": {"seconds": 5.00009, "end": 5.00009, "start": 0, "retransmits": 0, "socket": 16, "bits_per_second": 305319000.0, "bytes": 190827936}, "receiver": {"seconds": 5.00009, "end": 5.00009, "start": 0, "socket": 16, "bits_per_second": 303443000.0, "bytes": 189655617}}, {"sender": {"seconds": 5.00009, "end": 5.00009, "start": 0, "retransmits": 0, "socket": 18, "bits_per_second": 439236000.0, "bytes": 274527933}, "receiver": {"seconds": 5.00009, "end": 5.00009, "start": 0, "socket": 18, "bits_per_second": 437676000.0, "bytes": 273552492}}, {"sender": {"seconds": 5.00009, "end": 5.00009, "start": 0, "retransmits": 0, "socket": 20, "bits_per_second": 2529180000.0, "bytes": 1580768821}, "receiver": {"seconds": 5.00009, "end": 5.00009, "start": 0, "socket": 20, "bits_per_second": 2524920000.0, "bytes": 1578103459}}, {"sender": {"seconds": 5.00009, "end": 5.00009, "start": 0, "retransmits": 0, "socket": 22, "bits_per_second": 565517000.0, "bytes": 353454950}, "receiver": {"seconds": 5.00009, "end": 5.00009, "start": 0, "socket": 22, "bits_per_second": 563513000.0, "bytes": 352202090}}], "cpu_utilization_percent": {"host_system": 31.017, "host_user": 0.680432, "host_total": 31.6975, "remote_total": 12.0612, "remote_system": 11.4861, "remote_user": 0.575105}, "sum_sent": {"seconds": 5.00009, "end": 5.00009, "start": 0, "retransmits": 0, "bits_per_second": 7476150000.0, "bytes": 4672682994}, "sum_received": {"bytes": 4655511732, "seconds": 5.00009, "end": 5.00009, "start": 0, "bits_per_second": 7448680000.0}}, "start": {"tcp_mss_default": 8949, "connecting_to": {"port": 5201, "host": "172.31.67.222"}, "system_info": "Linux ip-172-31-70-219 3.13.0-156-generic #206-Ubuntu SMP Fri Aug 17 08:51:32 UTC 2018 x86_64 x86_64 x86_64 GNU/Linux\n", "test_start": {"duration": 5, "reverse": 0, "protocol": "TCP", "num_streams": 10, "blocks": 0, "bytes": 0, "omit": 0, "blksize": 131072}, "timestamp": {"time": "Sun, 07 Oct 2018 03:42:29 GMT", "timesecs": 1538883749}, "connected": [{"remote_host": "172.31.67.222", "local_port": 57252, "local_host": "172.31.70.219", "socket": 4, "remote_port": 5201}, {"remote_host": "172.31.67.222", "local_port": 57253, "local_host": "172.31.70.219", "socket": 6, "remote_port": 5201}, {"remote_host": "172.31.67.222", "local_port": 57254, "local_host": "172.31.70.219", "socket": 8, "remote_port": 5201}, {"remote_host": "172.31.67.222", "local_port": 57255, "local_host": "172.31.70.219", "socket": 10, "remote_port": 5201}, {"remote_host": "172.31.67.222", "local_port": 57256, "local_host": "172.31.70.219", "socket": 12, "remote_port": 5201}, {"remote_host": "172.31.67.222", "local_port": 57257, "local_host": "172.31.70.219", "socket": 14, "remote_port": 5201}, {"remote_host": "172.31.67.222", "local_port": 57258, "local_host": "172.31.70.219", "socket": 16, "remote_port": 5201}, {"remote_host": "172.31.67.222", "local_port": 57259, "local_host": "172.31.70.219", "socket": 18, "remote_port": 5201}, {"remote_host": "172.31.67.222", "local_port": 57260, "local_host": "172.31.70.219", "socket": 20, "remote_port": 5201}, {"remote_host": "172.31.67.222", "local_port": 57261, "local_host": "172.31.70.219", "socket": 22, "remote_port": 5201}], "version": "iperf 3.0.7", "cookie": "ip-172-31-70-219.1538883749.672987.3"}}