{"intervals": [{"streams": [{"seconds": 5.00009, "end": 5.00009, "start": 0, "snd_cwnd": 295317, "retransmits": 0, "socket": 4, "bits_per_second": 319294000.0, "bytes": 199562160, "omitted": false}, {"seconds": 5.0001, "end": 5.0001, "start": 0, "snd_cwnd": 304266, "retransmits": 0, "socket": 6, "bits_per_second": 319517000.0, "bytes": 199702181, "omitted": false}, {"seconds": 5.0001, "end": 5.0001, "start": 0, "snd_cwnd": 975441, "retransmits": 0, "socket": 8, "bits_per_second": 1089320000.0, "bytes": 680835677, "omitted": false}, {"seconds": 5.0001, "end": 5.0001, "start": 0, "snd_cwnd": 1915086, "retransmits": 0, "socket": 10, "bits_per_second": 2524130000.0, "bytes": 1577610441, "omitted": false}, {"seconds": 5.0001, "end": 5.0001, "start": 0, "snd_cwnd": 429552, "retransmits": 0, "socket": 12, "bits_per_second": 362357000.0, "bytes": 226477589, "omitted": false}, {"seconds": 5.0001, "end": 5.0001, "start": 0, "snd_cwnd": 572736, "retransmits": 0, "socket": 14, "bits_per_second": 419859000.0, "bytes": 262416773, "omitted": false}, {"seconds": 5.0001, "end": 5.0001, "start": 0, "snd_cwnd": 939645, "retransmits": 0, "socket": 16, "bits_per_second": 1405200000.0, "bytes": 878268515, "omitted": false}, {"seconds": 5.0001, "end": 5.0001, "start": 0, "snd_cwnd": 313215, "retransmits": 0, "socket": 18, "bits_per_second": 319947000.0, "bytes": 199970651, "omitted": false}, {"seconds": 5.0001, "end": 5.0001, "start": 0, "snd_cwnd": 474297, "retransmits": 0, "socket": 20, "bits_per_second": 416164000.0, "bytes": 260107931, "omitted": false}, {"seconds": 5.0001, "end": 5.0001, "start": 0, "snd_cwnd": 304266, "retransmits": 0, "socket": 22, "bits_per_second": 319159000.0, "bytes": 199478456, "omitted": false}], "sum": {"seconds": 5.00009, "end": 5.00009, "start": 0, "retransmits": 0, "bits_per_second": 7494950000.0, "omitted": false, "bytes": 4684430374}}], "end": {"streams": [{"sender": {"seconds": 5.00009, "end": 5.00009, "start": 0, "retransmits": 0, "socket": 4, "bits_per_second": 319294000.0, "bytes": 199562160}, "receiver": {"seconds": 5.00009, "end": 5.00009, "start": 0, "socket": 4, "bits_per_second": 317862000.0, "bytes": 198667260}}, {"sender": {"seconds": 5.00009, "end": 5.00009, "start": 0, "retransmits": 0, "socket": 6, "bits_per_second": 319518000.0, "bytes": 199702181}, "receiver": {"seconds": 5.00009, "end": 5.00009, "start": 0, "socket": 6, "bits_per_second": 318372000.0, "bytes": 198986261}}, {"sender": {"seconds": 5.00009, "end": 5.00009, "start": 0, "retransmits": 0, "socket": 8, "bits_per_second": 1089320000.0, "bytes": 680835677}, "receiver": {"seconds": 5.00009, "end": 5.00009, "start": 0, "socket": 8, "bits_per_second": 1084820000.0, "bytes": 678025691}}, {"sender": {"seconds": 5.00009, "end": 5.00009, "start": 0, "retransmits": 0, "socket": 10, "bits_per_second": 2524130000.0, "bytes": 1577610441}, "receiver": {"seconds": 5.00009, "end": 5.00009, "start": 0, "socket": 10, "bits_per_second": 2519410000.0, "bytes": 1574658094}}, {"sender": {"seconds": 5.00009, "end": 5.00009, "start": 0, "retransmits": 0, "socket": 12, "bits_per_second": 362358000.0, "bytes": 226477589}, "receiver": {"seconds": 5.00009, "end": 5.00009, "start": 0, "socket": 12, "bits_per_second": 359923000.0, "bytes": 224956259}}, {"sender": {"seconds": 5.00009, "end": 5.00009, "start": 0, "retransmits": 0, "socket": 14, "bits_per_second": 419859000.0, "bytes": 262416773}, "receiver": {"seconds": 5.00009, "end": 5.00009, "start": 0, "socket": 14, "bits_per_second": 416867000.0, "bytes": 260546432}}, {"sender": {"seconds": 5.00009, "end": 5.00009, "start": 0, "retransmits": 0, "socket": 16, "bits_per_second": 1405200000.0, "bytes": 878268515}, "receiver": {"seconds": 5.00009, "end": 5.00009, "start": 0, "socket": 16, "bits_per_second": 1400510000.0, "bytes": 875333243}}, {"sender": {"seconds": 5.00009, "end": 5.00009, "start": 0, "retransmits": 0, "socket": 18, "bits_per_second": 319947000.0, "bytes": 199970651}, "receiver": {"seconds": 5.00009, "end": 5.00009, "start": 0, "socket": 18, "bits_per_second": 318286000.0, "bytes": 198932567}}, {"sender": {"seconds": 5.00009, "end": 5.00009, "start": 0, "retransmits": 0, "socket": 20, "bits_per_second": 416165000.0, "bytes": 260107931}, "receiver": {"seconds": 5.00009, "end": 5.00009, "start": 0, "socket": 20, "bits_per_second": 413874000.0, "bytes": 258676091}}, {"sender": {"seconds": 5.00009, "end": 5.00009, "start": 0, "retransmits": 0, "socket": 22, "bits_per_second": 319160000.0, "bytes": 199478456}, "receiver": {"seconds": 5.00009, "end": 5.00009, "start": 0, "socket": 22, "bits_per_second": 318014000.0, "bytes": 198762536}}], "cpu_utilization_percent": {"host_system": 32.0278, "host_user": 0.0803236, "host_total": 32.1081, "remote_total": 12.2986, "remote_system": 11.3828, "remote_user": 0.75345}, "sum_sent": {"seconds": 5.00009, "end": 5.00009, "start": 0, "retransmits": 0, "bits_per_second": 7494950000.0, "bytes": 4684430374}, "sum_received": {"bytes": 4667544434, "seconds": 5.00009, "end": 5.00009, "start": 0, "bits_per_second": 7467940000.0}}, "start": {"tcp_mss_default": 8949, "connecting_to": {"port": 5201, "host": "172.31.67.222"}, "system_info": "Linux ip-172-31-70-219 3.13.0-156-generic #206-Ubuntu SMP Fri Aug 17 08:51:32 UTC 2018 x86_64 x86_64 x86_64 GNU/Linux\n", "test_start": {"duration": 5, "reverse": 0, "protocol": "TCP", "num_streams": 10, "blocks": 0, "bytes": 0, "omit": 0, "blksize": 131072}, "timestamp": {"time": "Sun, 07 Oct 2018 00:42:59 GMT", "timesecs": 1538872979}, "connected": [{"remote_host": "172.31.67.222", "local_port": 52944, "local_host": "172.31.70.219", "socket": 4, "remote_port": 5201}, {"remote_host": "172.31.67.222", "local_port": 52945, "local_host": "172.31.70.219", "socket": 6, "remote_port": 5201}, {"remote_host": "172.31.67.222", "local_port": 52946, "local_host": "172.31.70.219", "socket": 8, "remote_port": 5201}, {"remote_host": "172.31.67.222", "local_port": 52947, "local_host": "172.31.70.219", "socket": 10, "remote_port": 5201}, {"remote_host": "172.31.67.222", "local_port": 52948, "local_host": "172.31.70.219", "socket": 12, "remote_port": 5201}, {"remote_host": "172.31.67.222", "local_port": 52949, "local_host": "172.31.70.219", "socket": 14, "remote_port": 5201}, {"remote_host": "172.31.67.222", "local_port": 52950, "local_host": "172.31.70.219", "socket": 16, "remote_port": 5201}, {"remote_host": "172.31.67.222", "local_port": 52951, "local_host": "172.31.70.219", "socket": 18, "remote_port": 5201}, {"remote_host": "172.31.67.222", "local_port": 52952, "local_host": "172.31.70.219", "socket": 20, "remote_port": 5201}, {"remote_host": "172.31.67.222", "local_port": 52953, "local_host": "172.31.70.219", "socket": 22, "remote_port": 5201}], "version": "iperf 3.0.7", "cookie": "ip-172-31-70-219.1538872979.831845.6"}}