{"intervals": [{"streams": [{"seconds": 5.00009, "end": 5.00009, "start": 0, "snd_cwnd": 850155, "retransmits": 0, "socket": 4, "bits_per_second": 1165480000.0, "bytes": 728441734, "omitted": false}, {"seconds": 5.0001, "end": 5.0001, "start": 0, "snd_cwnd": 1440789, "retransmits": 0, "socket": 6, "bits_per_second": 1286120000.0, "bytes": 803839271, "omitted": false}, {"seconds": 5.0001, "end": 5.0001, "start": 0, "snd_cwnd": 769614, "retransmits": 0, "socket": 8, "bits_per_second": 840013000.0, "bytes": 525018852, "omitted": false}, {"seconds": 5.0001, "end": 5.0001, "start": 0, "snd_cwnd": 554838, "retransmits": 0, "socket": 10, "bits_per_second": 632582000.0, "bytes": 395372066, "omitted": false}, {"seconds": 5.0001, "end": 5.0001, "start": 0, "snd_cwnd": 429552, "retransmits": 0, "socket": 12, "bits_per_second": 497720000.0, "bytes": 311081435, "omitted": false}, {"seconds": 5.0001, "end": 5.0001, "start": 0, "snd_cwnd": 733818, "retransmits": 0, "socket": 14, "bits_per_second": 854937000.0, "bytes": 534346873, "omitted": false}, {"seconds": 5.0001, "end": 5.0001, "start": 0, "snd_cwnd": 420603, "retransmits": 0, "socket": 16, "bits_per_second": 577057000.0, "bytes": 360667844, "omitted": false}, {"seconds": 5.0001, "end": 5.0001, "start": 0, "snd_cwnd": 447450, "retransmits": 0, "socket": 18, "bits_per_second": 498627000.0, "bytes": 311648385, "omitted": false}, {"seconds": 5.0001, "end": 5.0001, "start": 0, "snd_cwnd": 1333401, "retransmits": 0, "socket": 20, "bits_per_second": 1260780000.0, "bytes": 788002626, "omitted": false}, {"seconds": 5.00011, "end": 5.00011, "start": 0, "snd_cwnd": 662226, "retransmits": 0, "socket": 22, "bits_per_second": 648847000.0, "bytes": 405538130, "omitted": false}], "sum": {"seconds": 5.00009, "end": 5.00009, "start": 0, "retransmits": 0, "bits_per_second": 8262170000.0, "omitted": false, "bytes": 5163957216}}], "end": {"streams": [{"sender": {"seconds": 5.00009, "end": 5.00009, "start": 0, "retransmits": 0, "socket": 4, "bits_per_second": 1165480000.0, "bytes": 728441734}, "receiver": {"seconds": 5.00009, "end": 5.00009, "start": 0, "socket": 4, "bits_per_second": 1161680000.0, "bytes": 726061300}}, {"sender": {"seconds": 5.00009, "end": 5.00009, "start": 0, "retransmits": 0, "socket": 6, "bits_per_second": 1286120000.0, "bytes": 803839271}, "receiver": {"seconds": 5.00009, "end": 5.00009, "start": 0, "socket": 6, "bits_per_second": 1280040000.0, "bytes": 800042683}}, {"sender": {"seconds": 5.00009, "end": 5.00009, "start": 0, "retransmits": 0, "socket": 8, "bits_per_second": 840014000.0, "bytes": 525018852}, "receiver": {"seconds": 5.00009, "end": 5.00009, "start": 0, "socket": 8, "bits_per_second": 836148000.0, "bytes": 522602622}}, {"sender": {"seconds": 5.00009, "end": 5.00009, "start": 0, "retransmits": 0, "socket": 10, "bits_per_second": 632583000.0, "bytes": 395372066}, "receiver": {"seconds": 5.00009, "end": 5.00009, "start": 0, "socket": 10, "bits_per_second": 630292000.0, "bytes": 393940226}}, {"sender": {"seconds": 5.00009, "end": 5.00009, "start": 0, "retransmits": 0, "socket": 12, "bits_per_second": 497721000.0, "bytes": 311081435}, "receiver": {"seconds": 5.00009, "end": 5.00009, "start": 0, "socket": 12, "bits_per_second": 496132000.0, "bytes": 310088096}}, {"sender": {"seconds": 5.00009, "end": 5.00009, "start": 0, "retransmits": 0, "socket": 14, "bits_per_second": 854939000.0, "bytes": 534346873}, "receiver": {"seconds": 5.00009, "end": 5.00009, "start": 0, "socket": 14, "bits_per_second": 851459000.0, "bytes": 532172266}}, {"sender": {"seconds": 5.00009, "end": 5.00009, "start": 0, "retransmits": 0, "socket": 16, "bits_per_second": 577058000.0, "bytes": 360667844}, "receiver": {"seconds": 5.00009, "end": 5.00009, "start": 0, "socket": 16, "bits_per_second": 574896000.0, "bytes": 359316545}}, {"sender": {"seconds": 5.00009, "end": 5.00009, "start": 0, "retransmits": 0, "socket": 18, "bits_per_second": 498628000.0, "bytes": 311648385}, "receiver": {"seconds": 5.00009, "end": 5.00009, "start": 0, "socket": 18, "bits_per_second": 496308000.0, "bytes": 310198647}}, {"sender": {"seconds": 5.00009, "end": 5.00009, "start": 0, "retransmits": 0, "socket": 20, "bits_per_second": 1260780000.0, "bytes": 788002626}, "receiver": {"seconds": 5.00009, "end": 5.00009, "start": 0, "socket": 20, "bits_per_second": 1255190000.0, "bytes": 784507219}}, {"sender": {"seconds": 5.00009, "end": 5.00009, "start": 0, "retransmits": 0, "socket": 22, "bits_per_second": 648849000.0, "bytes": 405538130}, "receiver": {"seconds": 5.00009, "end": 5.00009, "start": 0, "socket": 22, "bits_per_second": 645155000.0, "bytes": 403229288}}], "cpu_utilization_percent": {"host_system": 35.0947, "host_user": 0.329751, "host_total": 35.4245, "remote_total": 13.2075, "remote_system": 12.8869, "remote_user": 0.320582}, "sum_sent": {"seconds": 5.00009, "end": 5.00009, "start": 0, "retransmits": 0, "bits_per_second": 8262170000.0, "bytes": 5163957216}, "sum_received": {"bytes": 5142158892, "seconds": 5.00009, "end": 5.00009, "start": 0, "bits_per_second": 8227300000.0}}, "start": {"tcp_mss_default": 8949, "connecting_to": {"port": 5201, "host": "172.31.67.222"}, "system_info": "Linux ip-172-31-70-219 3.13.0-156-generic #206-Ubuntu SMP Fri Aug 17 08:51:32 UTC 2018 x86_64 x86_64 x86_64 GNU/Linux\n", "test_start": {"duration": 5, "reverse": 0, "protocol": "TCP", "num_streams": 10, "blocks": 0, "bytes": 0, "omit": 0, "blksize": 131072}, "timestamp": {"time": "Mon, 08 Oct 2018 06:00:59 GMT", "timesecs": 1538978459}, "connected": [{"remote_host": "172.31.67.222", "local_port": 38674, "local_host": "172.31.70.219", "socket": 4, "remote_port": 5201}, {"remote_host": "172.31.67.222", "local_port": 38675, "local_host": "172.31.70.219", "socket": 6, "remote_port": 5201}, {"remote_host": "172.31.67.222", "local_port": 38676, "local_host": "172.31.70.219", "socket": 8, "remote_port": 5201}, {"remote_host": "172.31.67.222", "local_port": 38677, "local_host": "172.31.70.219", "socket": 10, "remote_port": 5201}, {"remote_host": "172.31.67.222", "local_port": 38678, "local_host": "172.31.70.219", "socket": 12, "remote_port": 5201}, {"remote_host": "172.31.67.222", "local_port": 38679, "local_host": "172.31.70.219", "socket": 14, "remote_port": 5201}, {"remote_host": "172.31.67.222", "local_port": 38680, "local_host": "172.31.70.219", "socket": 16, "remote_port": 5201}, {"remote_host": "172.31.67.222", "local_port": 38681, "local_host": "172.31.70.219", "socket": 18, "remote_port": 5201}, {"remote_host": "172.31.67.222", "local_port": 38682, "local_host": "172.31.70.219", "socket": 20, "remote_port": 5201}, {"remote_host": "172.31.67.222", "local_port": 38683, "local_host": "172.31.70.219", "socket": 22, "remote_port": 5201}], "version": "iperf 3.0.7", "cookie": "ip-172-31-70-219.1538978459.671368.6"}}